haillo/__init__.py
haillo/__main__.py
haillo/config.py
haillo/haillo.py
haillo/hutils.py
haillo/logger.py
haillo/package.py
haillo/data/haillo.1
haillo/static/context.css
haillo/static/context.js
haillo/static/manifest.json
haillo/static/sidebar.css
haillo/static/sidebar.js
haillo/static/icons/icon_144x144.png
haillo/templates/chat_history.html
haillo/templates/index.html
haillo/templates/sidebar.html
haillo-0.4.0.dist-info/licenses/LICENSE.txt
haillo-0.4.0.dist-info/METADATA
haillo-0.4.0.dist-info/WHEEL
haillo-0.4.0.dist-info/entry_points.txt
haillo-0.4.0.dist-info/top_level.txt
haillo-0.4.0.dist-info/RECORD
