Metadata-Version: 2.4
Name: haillo
Version: 0.4.0
Summary: Haillo is a web frontend for hai (hcli_hai), the HCLI command line AI chat application.
Author-email: Jeff Michaud <cometaj2@proton.me>
License: MIT
Project-URL: Homepage, https://github.com/cometaj2/haillo
Keywords: ai,llm,web,ui,cli,client,server,connector,hypermedia,rest,generic,development
Classifier: Development Status :: 4 - Beta
Classifier: Intended Audience :: Developers
Classifier: Topic :: Software Development
Classifier: License :: OSI Approved :: MIT License
Classifier: Programming Language :: Python :: 3.8
Classifier: Programming Language :: Python :: 3.9
Classifier: Programming Language :: Python :: 3.10
Classifier: Programming Language :: Python :: 3.11
Classifier: Programming Language :: Python :: 3.12
License-File: LICENSE.txt
Requires-Dist: flask==3.1.0
Requires-Dist: huckle<6.0.0,>=5.7.0
Requires-Dist: hcli_hai<4.0.0,>=3.4.2
Dynamic: license-file
